{
    "h"     : 150,
    "minh"  : 40,
    "maxh"  : 207,
    "w"     : 60,
    "minw"  : 35,
    "maxw"  : 75,
    "pd"    : [2, 2, 2, 2],
    "row"   : 50,
    "gap"   : 2,
    "grid"  : [1, 2],
    "child" : [
    {
    "pd"    : [2, 2, 2, 2],
    "child" : [
        {
        "pd"       : [3, 3, 3, 3],
        "glass"    : true
        }
    ]
    },
    {
        "pd"    : [2, 2, 2, 2],
        "child" : [
            {
            "pd"       : [3, 3, 3, 3],
            "glass"    : true,
            "triangle" : "left"
            }
        ]
    }
]
}